pylibconfig2
