Metadata-Version: 1.1
Name: pylibconfig2
Version: 0.2.0
Summary: Pure python library for libconfig syntax.
Home-page: https://github.com/heinzK1X/pylibconfig2
Author: Heiner Tholen
Author-email: github@heinertholen.com
License: GPLv3
Keywords: libconfig libconfig++ pylibconfig2 pylibconfig config
Platform: UNKNOWN
Requires: pyparsing
